hikvision_openapi_signer.py
hikvision_openapi_signer-1.0.0.dist-info/licenses/LICENSE.txt
hikvision_openapi_signer-1.0.0.dist-info/METADATA
hikvision_openapi_signer-1.0.0.dist-info/WHEEL
hikvision_openapi_signer-1.0.0.dist-info/top_level.txt
hikvision_openapi_signer-1.0.0.dist-info/RECORD
