Metadata-Version: 2.4
Name: Hikvision-OpenAPI-Signer
Version: 1.0.0
Summary: 海康威视iSecure Center综合安防管理平台OpenAPI网关Artemis接口请求签名模块
Author: Accurio
License-Expression: Apache-2.0
Project-URL: Repository, https://github.com/Accurio/Hikvision-OpenAPI-Signer
Keywords: Hikvision,iSecure Center,OpenAPI,Artemis
Classifier: Intended Audience :: Information Technology
Classifier: Natural Language :: Chinese (Simplified)
Classifier: Operating System :: OS Independent
Classifier: Programming Language :: Python
Classifier: Programming Language :: Python :: 3
Classifier: Programming Language :: Python :: 3 :: Only
Requires-Python: >=3.9
License-File: LICENSE.txt
Dynamic: license-file
